django_drf_jwt/__init__.py
django_drf_jwt/admin.py
django_drf_jwt/apps.py
django_drf_jwt/authentication.py
django_drf_jwt/handlers.py
django_drf_jwt/models.py
django_drf_jwt/serializers.py
django_drf_jwt/settings.py
django_drf_jwt/urls.py
django_drf_jwt/views.py
django_drf_jwt/migrations/__init__.py
django_drf_mjwt-0.0.1.dist-info/licenses/LICENSE
tests/__init__.py
tests/models.py
tests/settings.py
tests/test_api.py
tests/urls.py
django_drf_mjwt-0.0.1.dist-info/METADATA
django_drf_mjwt-0.0.1.dist-info/WHEEL
django_drf_mjwt-0.0.1.dist-info/top_level.txt
django_drf_mjwt-0.0.1.dist-info/RECORD
